scr/__init__.py
scr/example/__init__.py
scr/example/sentinel_2_band_downloader_example.py
scr/main/__init__.py
scr/main/sentinel_2_band_downloader.py
scr/misc/__init__.py
scr/misc/connections.py
scr/misc/dates.py
scr/misc/files.py
scr/misc/utils.py
sentinel_2_band_downloader-0.3.4.dist-info/licenses/LICENSE
sentinel_2_band_downloader-0.3.4.dist-info/METADATA
sentinel_2_band_downloader-0.3.4.dist-info/WHEEL
sentinel_2_band_downloader-0.3.4.dist-info/top_level.txt
sentinel_2_band_downloader-0.3.4.dist-info/RECORD
