Metadata-Version: 2.4
Name: Sentinel_2_band_downloader
Version: 0.3.4
Summary: Utility for searching and downloading satellite images of Sentinel 2
Author-email: Beatriz Nattrodt DAvila <beatriznattrodt@gmail.com>
Requires-Python: >=3.10
License-File: LICENSE
Requires-Dist: requests==2.31.0
Requires-Dist: loguru==0.7.2
Requires-Dist: tqdm==4.66.1
Dynamic: license-file
